{
  "suggestion": {
    "keywords": [],
    "cities": []
  },
  "count": "94",
  "infocode": "10000",
  "pois": [
    {
      "parent": "B020015S07",
      "distance": [],
      "keytag": "地面停车场",
      "importance": [],
      "biz_ext": [],
      "type": "交通设施服务;停车场;公共停车场",
      "parking_type": "地面",
      "photos": [],
      "building": [],
      "typecode": "150904",
      "shopinfo": "2",
      "poiweight": [],
      "adname": "张家港市",
      "featured_reviews_remake": [],
      "tel": [],
      "id": "B0FFGJBMSA",
      "address": "长兴中路1号张家港市老年公寓",
      "space_num": [],
      "pname": "江苏省",
      "biz_type": [],
      "cityname": "苏州市",
      "childtype": "305",
      "atag": [],
      "name": "张家港市老年公寓停车场",
      "location": "120.584206,31.886183",
      "shopid": [],
      "favorite_num": [],
      "featured_reviews": []
    },
    {
      "parent": [],
      "distance": [],
      "keytag": "住宅区",
      "importance": [],
      "biz_ext": [],
      "type": "商务住宅;商务住宅相关;商务住宅相关",
      "photos": [],
      "building": [],
      "typecode": "120000",
      "shopinfo": "0",
      "poiweight": [],
      "adname": "张家港市",
      "featured_reviews_remake": [],
      "tel": [],
      "id": "B0L66ULLOQ",
      "address": "杨舍镇通运路110号",
      "space_num": [],
      "pname": "江苏省",
      "biz_type": [],
      "cityname": "苏州市",
      "childtype": [],
      "atag": [],
      "name": "悠家公寓",
      "location": "120.538697,31.877146",
      "shopid": [],
      "favorite_num": [],
      "featured_reviews": []
    },
    {
      "parent": [],
      "distance": [],
      "keytag": "住宿服务,旅馆招待所,旅馆招待所",
      "importance": [],
      "biz_ext": [],
      "type": "住宿服务;旅馆招待所;旅馆招待所",
      "photos": [],
      "building": [],
      "typecode": "100200",
      "shopinfo": "0",
      "poiweight": [],
      "adname": "张家港市",
      "featured_reviews_remake": [],
      "tel": [],
      "id": "B0I0BOHTQQ",
      "address": "勤丰苑东北门旁",
      "space_num": [],
      "pname": "江苏省",
      "biz_type": "hotel",
      "cityname": "苏州市",
      "childtype": [],
      "atag": [],
      "name": "汇金公寓(万达广场店)",
      "location": "120.573001,31.873003",
      "shopid": [],
      "favorite_num": [],
      "featured_reviews": []
    },
    {
      "parent": [],
      "distance": [],
      "keytag": "住宅区",
      "importance": [],
      "biz_ext": [],
      "type": "商务住宅;住宅区;住宅小区",
      "photos": [],
      "building": [],
      "typecode": "120302",
      "shopinfo": "0",
      "poiweight": [],
      "adname": "张家港市",
      "featured_reviews_remake": [],
      "tel": [],
      "id": "B02001BEJ2",
      "address": "杨舍镇中兴路与港城大道交叉口东100米",
      "space_num": [],
      "pname": "江苏省",
      "biz_type": [],
      "cityname": "苏州市",
      "childtype": [],
      "atag": [],
      "name": "港城精英公寓",
      "location": "120.541423,31.894564",
      "shopid": [],
      "favorite_num": [],
      "featured_reviews": []
    },
    {
      "parent": [],
      "distance": [],
      "keytag": "住宅区",
      "importance": [],
      "biz_ext": [],
      "type": "商务住宅;商务住宅相关;商务住宅相关",
      "photos": [],
      "building": [],
      "typecode": "120000",
      "shopinfo": "0",
      "poiweight": [],
      "adname": "张家港市",
      "featured_reviews_remake": [],
      "tel": [],
      "id": "B0FFME0XS6",
      "address": "国泰北路与张杨公路交叉口北260米",
      "space_num": [],
      "pname": "江苏省",
      "biz_type": [],
      "cityname": "苏州市",
      "childtype": [],
      "atag": [],
      "name": "人才公寓",
      "location": "120.525774,31.891031",
      "shopid": [],
      "favorite_num": [],
      "featured_reviews": []
    },
    {
      "parent": [],
      "distance": [],
      "keytag": "住宅区",
      "importance": [],
      "biz_ext": [],
      "type": "商务住宅;住宅区;住宅小区",
      "photos": [],
      "building": [],
      "typecode": "120302",
      "shopinfo": "0",
      "poiweight": [],
      "adname": "张家港市",
      "featured_reviews_remake": [],
      "tel": [],
      "id": "B0FFH9H7IR",
      "address": "杨舍镇西塘公路与河南路交叉口东260米",
      "space_num": [],
      "pname": "江苏省",
      "biz_type": [],
      "cityname": "苏州市",
      "childtype": [],
      "atag": [],
      "name": "西塘公寓",
      "location": "120.544545,31.810310",
      "shopid": [],
      "favorite_num": [],
      "featured_reviews": []
    },
    {
      "parent": [],
      "distance": [],
      "keytag": "公交站",
      "importance": [],
      "biz_ext": [],
      "type": "交通设施服务;公交车站;公交车站相关",
      "photos": [],
      "building": [],
      "typecode": "150700",
      "shopinfo": "2",
      "poiweight": [],
      "adname": "张家港市",
      "featured_reviews_remake": [],
      "tel": [],
      "id": "BV10887128",
      "address": "张家港35路",
      "space_num": [],
      "pname": "江苏省",
      "biz_type": [],
      "cityname": "苏州市",
      "childtype": [],
      "atag": [],
      "name": "南庄公寓(公交站)",
      "location": "120.538958,31.825777",
      "shopid": [],
      "favorite_num": [],
      "featured_reviews": []
    },
    {
      "parent": [],
      "distance": [],
      "keytag": "住宿服务,旅馆招待所,旅馆招待所",
      "importance": [],
      "biz_ext": [],
      "type": "住宿服务;旅馆招待所;旅馆招待所",
      "photos": [],
      "building": [],
      "typecode": "100200",
      "shopinfo": "0",
      "poiweight": [],
      "adname": "张家港市",
      "featured_reviews_remake": [],
      "tel": [],
      "id": "B0IGNSZICU",
      "address": "通运路与积善桥弄交叉口西北120米",
      "space_num": [],
      "pname": "江苏省",
      "biz_type": "hotel",
      "cityname": "苏州市",
      "childtype": [],
      "atag": [],
      "name": "温馨公寓",
      "location": "120.539107,31.876232",
      "shopid": [],
      "favorite_num": [],
      "featured_reviews": []
    },
    {
      "parent": [],
      "distance": [],
      "keytag": "住宿服务,旅馆招待所,旅馆招待所",
      "importance": [],
      "biz_ext": [],
      "type": "住宿服务;旅馆招待所;旅馆招待所",
      "photos": [],
      "building": [],
      "typecode": "100200",
      "shopinfo": "0",
      "poiweight": [],
      "adname": "张家港市",
      "featured_reviews_remake": [],
      "tel": [],
      "id": "B0J3O5W9B8",
      "address": "步行街142号3层",
      "space_num": [],
      "pname": "江苏省",
      "biz_type": "hotel",
      "cityname": "苏州市",
      "childtype": [],
      "atag": [],
      "name": "金悦公寓(步行街店)",
      "location": "120.540547,31.863757",
      "shopid": [],
      "favorite_num": [],
      "featured_reviews": []
    },
    {
      "parent": [],
      "distance": [],
      "keytag": "旅馆",
      "importance": [],
      "biz_ext": [],
      "type": "住宿服务;旅馆招待所;旅馆招待所|住宿服务;宾馆酒店;宾馆酒店",
      "photos": [],
      "building": [],
      "typecode": "100200|100100",
      "shopinfo": "1",
      "poiweight": [],
      "adname": "张家港市",
      "featured_reviews_remake": [],
      "tel": [],
      "id": "B02000JVV5",
      "address": "天台北路71号",
      "space_num": [],
      "pname": "江苏省",
      "biz_type": "hotel",
      "cityname": "苏州市",
      "childtype": [],
      "atag": [],
      "name": "扬子江公寓",
      "location": "120.415536,31.959379",
      "shopid": [],
      "favorite_num": [],
      "featured_reviews": []
    },
    {
      "parent": [],
      "distance": [],
      "keytag": "住宅区",
      "importance": [],
      "biz_ext": [],
      "type": "商务住宅;住宅区;住宅小区",
      "photos": [],
      "building": [],
      "typecode": "120302",
      "shopinfo": "0",
      "poiweight": [],
      "adname": "张家港市",
      "featured_reviews_remake": [],
      "tel": [],
      "id": "B0FFL91QK1",
      "address": "南丰镇南丰南路17号",
      "space_num": [],
      "pname": "江苏省",
      "biz_type": [],
      "cityname": "苏州市",
      "childtype": [],
      "atag": [],
      "name": "创业公寓",
      "location": "120.658309,31.889801",
      "shopid": [],
      "favorite_num": [],
      "featured_reviews": []
    },
    {
      "parent": [],
      "distance": [],
      "keytag": "宿舍",
      "importance": [],
      "biz_ext": [],
      "type": "商务住宅;住宅区;宿舍",
      "photos": [],
      "building": [],
      "typecode": "120303",
      "shopinfo": "0",
      "poiweight": [],
      "adname": "张家港市",
      "featured_reviews_remake": [],
      "tel": [],
      "id": "B0FFKN6SWP",
      "address": "五棵松路与330村道交叉口西北120米",
      "space_num": [],
      "pname": "江苏省",
      "biz_type": [],
      "cityname": "苏州市",
      "childtype": [],
      "atag": [],
      "name": "张家港联合铜业有限公司职工公寓区",
      "location": "120.699804,31.950981",
      "shopid": [],
      "favorite_num": [],
      "featured_reviews": []
    },
    {
      "parent": [],
      "distance": [],
      "keytag": "养老院",
      "importance": [],
      "biz_ext": [],
      "type": "体育休闲服务;度假疗养场所;疗养院",
      "photos": [],
      "building": [],
      "typecode": "080402",
      "shopinfo": "0",
      "poiweight": [],
      "adname": "张家港市",
      "featured_reviews_remake": [],
      "tel": [],
      "id": "B0FFJWYAP8",
      "address": "红光村16组",
      "space_num": [],
      "pname": "江苏省",
      "biz_type": [],
      "cityname": "苏州市",
      "childtype": [],
      "atag": [],
      "name": "张家港市锦丰镇锦虹老年公寓",
      "location": "120.592762,31.973680",
      "shopid": [],
      "favorite_num": [],
      "featured_reviews": []
    },
    {
      "parent": [],
      "distance": [],
      "keytag": "住宅区",
      "importance": [],
      "biz_ext": [],
      "type": "商务住宅;住宅区;住宅小区",
      "photos": [],
      "building": [],
      "typecode": "120302",
      "shopinfo": "0",
      "poiweight": [],
      "adname": "张家港市",
      "featured_reviews_remake": [],
      "tel": [],
      "id": "B0FFFTO7D5",
      "address": "张家港经济技术开发区上海联都超市北(东南大道西)",
      "space_num": [],
      "pname": "江苏省",
      "biz_type": [],
      "cityname": "苏州市",
      "childtype": [],
      "atag": [],
      "name": "汤联公寓",
      "location": "120.567376,31.825516",
      "shopid": [],
      "favorite_num": [],
      "featured_reviews": []
    },
    {
      "parent": [],
      "distance": [],
      "keytag": "住宅区",
      "importance": [],
      "biz_ext": [],
      "type": "商务住宅;住宅区;住宅小区",
      "photos": [],
      "building": [],
      "typecode": "120302",
      "shopinfo": "0",
      "poiweight": [],
      "adname": "张家港市",
      "featured_reviews_remake": [],
      "tel": [],
      "id": "B0LBLCBYWD",
      "address": "杨舍镇振兴路与长安北路交叉口西220米",
      "space_num": [],
      "pname": "江苏省",
      "biz_type": [],
      "cityname": "苏州市",
      "childtype": [],
      "atag": [],
      "name": "中大公寓",
      "location": "120.552575,31.897425",
      "shopid": [],
      "favorite_num": [],
      "featured_reviews": []
    },
    {
      "parent": [],
      "distance": [],
      "keytag": "住宅区",
      "importance": [],
      "biz_ext": [],
      "type": "商务住宅;住宅区;住宅小区",
      "photos": [],
      "building": [],
      "typecode": "120302",
      "shopinfo": "0",
      "poiweight": [],
      "adname": "张家港市",
      "featured_reviews_remake": [],
      "tel": [],
      "id": "B0FFHRKNX9",
      "address": "锦丰镇元宝街与合兴河西路交叉口西140米",
      "space_num": [],
      "pname": "江苏省",
      "biz_type": [],
      "cityname": "苏州市",
      "childtype": [],
      "atag": [],
      "name": "张家港合兴星火公寓",
      "location": "120.593385,31.923201",
      "shopid": [],
      "favorite_num": [],
      "featured_reviews": []
    },
    {
      "parent": [],
      "distance": [],
      "keytag": "住宅区",
      "importance": [],
      "biz_ext": [],
      "type": "商务住宅;住宅区;住宅小区|住宿服务;旅馆招待所;旅馆招待所",
      "photos": [],
      "building": [],
      "typecode": "120302|100200",
      "shopinfo": "0",
      "poiweight": [],
      "adname": "张家港市",
      "featured_reviews_remake": [],
      "tel": [],
      "id": "B0FFMA6RVI",
      "address": "金港街道江海中路与滩上路交叉口东北80米",
      "space_num": [],
      "pname": "江苏省",
      "biz_type": [],
      "cityname": "苏州市",
      "childtype": [],
      "atag": [],
      "name": "攀华公寓",
      "location": "120.418380,31.950606",
      "shopid": [],
      "favorite_num": [],
      "featured_reviews": []
    },
    {
      "parent": [],
      "distance": [],
      "keytag": "住宅区",
      "importance": [],
      "biz_ext": [],
      "type": "商务住宅;住宅区;住宅小区",
      "photos": [],
      "building": [],
      "typecode": "120302",
      "shopinfo": "0",
      "poiweight": [],
      "adname": "张家港市",
      "featured_reviews_remake": [],
      "tel": [],
      "id": "B02000JUJV",
      "address": "锦丰镇锦中路",
      "space_num": [],
      "pname": "江苏省",
      "biz_type": [],
      "cityname": "苏州市",
      "childtype": [],
      "atag": [],
      "name": "金鹿公寓",
      "location": "120.643544,31.962616",
      "shopid": [],
      "favorite_num": [],
      "featured_reviews": []
    },
    {
      "parent": [],
      "distance": [],
      "keytag": "住宅区",
      "importance": [],
      "biz_ext": [],
      "type": "商务住宅;住宅区;住宅小区",
      "photos": [],
      "building": [],
      "typecode": "120302",
      "shopinfo": "0",
      "poiweight": [],
      "adname": "张家港市",
      "featured_reviews_remake": [],
      "tel": [],
      "id": "B0FFICEL5F",
      "address": "杨舍镇新丰河西路3号",
      "space_num": [],
      "pname": "江苏省",
      "biz_type": [],
      "cityname": "苏州市",
      "childtype": [],
      "atag": [],
      "name": "舒馨公寓",
      "location": "120.542865,31.824234",
      "shopid": [],
      "favorite_num": [],
      "featured_reviews": []
    },
    {
      "parent": [],
      "distance": [],
      "keytag": "公寓式酒店",
      "importance": [],
      "biz_ext": [],
      "type": "商务住宅;商务住宅相关;商务住宅相关",
      "photos": [],
      "building": [],
      "typecode": "120000",
      "shopinfo": "0",
      "poiweight": [],
      "adname": "张家港市",
      "featured_reviews_remake": [],
      "tel": "18136196000",
      "id": "B0H1R5A7U4",
      "address": "人民路",
      "space_num": [],
      "pname": "江苏省",
      "biz_type": [],
      "cityname": "苏州市",
      "childtype": [],
      "atag": [],
      "name": "金悦公寓",
      "location": "120.727980,31.904078",
      "shopid": [],
      "favorite_num": [],
      "featured_reviews": []
    }
  ],
  "status": "1",
  "info": "OK"
}