{
  "suggestion": {
    "keywords": [],
    "cities": []
  },
  "count": "900",
  "infocode": "10000",
  "pois": [
    {
      "parent": [],
      "distance": [],
      "keytag": "道路",
      "importance": [],
      "biz_ext": [],
      "type": "地名地址信息;交通地名;道路名",
      "photos": [],
      "building": [],
      "typecode": "190301",
      "shopinfo": "2",
      "poiweight": [],
      "adname": "阜宁县",
      "featured_reviews_remake": [],
      "tel": [],
      "id": "BZBAQN005G",
      "address": "阜宁县",
      "space_num": [],
      "pname": "江苏省",
      "biz_type": [],
      "cityname": "盐城市",
      "childtype": [],
      "atag": [],
      "name": "阜城大街",
      "location": "119.797811,33.781826",
      "shopid": [],
      "favorite_num": [],
      "featured_reviews": []
    },
    {
      "parent": [],
      "distance": [],
      "keytag": "道路",
      "importance": [],
      "biz_ext": [],
      "type": "地名地址信息;交通地名;道路名",
      "photos": [],
      "building": [],
      "typecode": "190301",
      "shopinfo": "2",
      "poiweight": [],
      "adname": "阜宁县",
      "featured_reviews_remake": [],
      "tel": [],
      "id": "B02030IJ89",
      "address": "阜宁县",
      "space_num": [],
      "pname": "江苏省",
      "biz_type": [],
      "cityname": "盐城市",
      "childtype": [],
      "atag": [],
      "name": "阜城东大街",
      "location": "119.821556,33.784105",
      "shopid": [],
      "favorite_num": [],
      "featured_reviews": []
    },
    {
      "parent": "B0JUFZS52O",
      "distance": [],
      "keytag": "道路",
      "importance": [],
      "biz_ext": [],
      "type": "地名地址信息;交通地名;道路名",
      "photos": [],
      "building": [],
      "typecode": "190301",
      "shopinfo": "2",
      "poiweight": [],
      "adname": "阜宁县",
      "featured_reviews_remake": [],
      "tel": [],
      "id": "BZBAQM0009",
      "address": "阜宁县",
      "space_num": [],
      "pname": "江苏省",
      "biz_type": [],
      "cityname": "盐城市",
      "childtype": "7",
      "atag": [],
      "name": "329省道",
      "location": "119.730601,33.792393",
      "shopid": [],
      "favorite_num": [],
      "featured_reviews": []
    },
    {
      "parent": [],
      "distance": [],
      "keytag": "道路",
      "importance": [],
      "biz_ext": [],
      "type": "地名地址信息;交通地名;道路名",
      "photos": [],
      "building": [],
      "typecode": "190301",
      "shopinfo": "2",
      "poiweight": [],
      "adname": "阜宁县",
      "featured_reviews_remake": [],
      "tel": [],
      "id": "B020315J3Q",
      "address": "阜宁县",
      "space_num": [],
      "pname": "江苏省",
      "biz_type": [],
      "cityname": "盐城市",
      "childtype": [],
      "atag": [],
      "name": "澳门路",
      "location": "119.800925,33.768835",
      "shopid": [],
      "favorite_num": [],
      "featured_reviews": []
    },
    {
      "parent": [],
      "distance": [],
      "keytag": "收费站",
      "importance": [],
      "biz_ext": [],
      "type": "道路附属设施;收费站;收费站",
      "photos": [],
      "building": [],
      "typecode": "180200",
      "shopinfo": "2",
      "poiweight": [],
      "adname": "阜宁县",
      "featured_reviews_remake": [],
      "tel": [],
      "id": "B0FFGQR621",
      "address": "阜宁县",
      "space_num": [],
      "pname": "江苏省",
      "biz_type": [],
      "cityname": "盐城市",
      "childtype": [],
      "atag": [],
      "name": "东沟收费站(S35阜溧高速入口)",
      "location": "119.703732,33.602229",
      "shopid": [],
      "favorite_num": [],
      "featured_reviews": []
    },
    {
      "parent": [],
      "distance": [],
      "keytag": "道路",
      "importance": [],
      "biz_ext": [],
      "type": "地名地址信息;交通地名;环岛名",
      "photos": [],
      "building": [],
      "typecode": "190303",
      "shopinfo": "2",
      "poiweight": [],
      "adname": "阜宁县",
      "featured_reviews_remake": [],
      "tel": [],
      "id": "B0FFGA6LX0",
      "address": "阜宁县",
      "space_num": [],
      "pname": "江苏省",
      "biz_type": [],
      "cityname": "盐城市",
      "childtype": [],
      "atag": [],
      "name": "西园盘",
      "location": "119.766429,33.783277",
      "shopid": [],
      "favorite_num": [],
      "featured_reviews": []
    },
    {
      "parent": "BZB7QP002D",
      "distance": [],
      "keytag": "道路",
      "importance": [],
      "biz_ext": [],
      "type": "地名地址信息;交通地名;道路名",
      "photos": [],
      "building": [],
      "typecode": "190301",
      "shopinfo": "2",
      "poiweight": [],
      "adname": "阜宁县",
      "featured_reviews_remake": [],
      "tel": [],
      "id": "BZB9QN0001",
      "address": "阜宁县",
      "space_num": [],
      "pname": "江苏省",
      "biz_type": [],
      "cityname": "盐城市",
      "childtype": "7",
      "atag": [],
      "name": "通榆路",
      "location": "119.836178,33.745795",
      "shopid": [],
      "favorite_num": [],
      "featured_reviews": []
    },
    {
      "parent": [],
      "distance": [],
      "keytag": "道路",
      "importance": [],
      "biz_ext": [],
      "type": "地名地址信息;交通地名;道路名",
      "photos": [],
      "building": [],
      "typecode": "190301",
      "shopinfo": "2",
      "poiweight": [],
      "adname": "阜宁县",
      "featured_reviews_remake": [],
      "tel": [],
      "id": "BZBAQN006W",
      "address": "阜宁县",
      "space_num": [],
      "pname": "江苏省",
      "biz_type": [],
      "cityname": "盐城市",
      "childtype": [],
      "atag": [],
      "name": "阜城西大街",
      "location": "119.773740,33.783130",
      "shopid": [],
      "favorite_num": [],
      "featured_reviews": []
    },
    {
      "parent": [],
      "distance": [],
      "keytag": "城市次干路",
      "importance": [],
      "biz_ext": [],
      "type": "地名地址信息;交通地名;道路名",
      "photos": [],
      "building": [],
      "typecode": "190301",
      "shopinfo": "2",
      "poiweight": [],
      "adname": "阜宁县",
      "featured_reviews_remake": [],
      "tel": [],
      "id": "B0FFG7N5GF",
      "address": "阜宁县",
      "space_num": [],
      "pname": "江苏省",
      "biz_type": [],
      "cityname": "盐城市",
      "childtype": [],
      "atag": [],
      "name": "太原路",
      "location": "119.791057,33.751227",
      "shopid": [],
      "favorite_num": [],
      "featured_reviews": []
    },
    {
      "parent": [],
      "distance": [],
      "keytag": "门牌地址",
      "importance": [],
      "biz_ext": [],
      "type": "地名地址信息;门牌信息;门牌信息",
      "photos": [],
      "building": [],
      "typecode": "190400",
      "shopinfo": "2",
      "poiweight": [],
      "adname": "阜宁县",
      "featured_reviews_remake": [],
      "tel": [],
      "id": "B0K69UOJKX",
      "address": "阜宁县",
      "space_num": [],
      "pname": "江苏省",
      "biz_type": [],
      "cityname": "盐城市",
      "childtype": [],
      "atag": [],
      "name": "新东路38号",
      "location": "119.692983,33.550408",
      "shopid": [],
      "favorite_num": [],
      "featured_reviews": []
    },
    {
      "parent": [],
      "distance": [],
      "keytag": "地名地址信息,地名地址信息,地名地址信息",
      "importance": [],
      "biz_ext": [],
      "type": "地名地址信息;地名地址信息;地名地址信息",
      "photos": [],
      "building": [],
      "typecode": "190000",
      "shopinfo": "2",
      "poiweight": [],
      "adname": "阜宁县",
      "featured_reviews_remake": [],
      "tel": [],
      "id": "B0FFJ8JTAY",
      "address": "阜宁县",
      "space_num": [],
      "pname": "江苏省",
      "biz_type": [],
      "cityname": "盐城市",
      "childtype": [],
      "atag": [],
      "name": "立新新村",
      "location": "119.880430,33.744534",
      "shopid": [],
      "favorite_num": [],
      "featured_reviews": []
    },
    {
      "parent": [],
      "distance": [],
      "keytag": "桥",
      "importance": [],
      "biz_ext": [],
      "type": "地名地址信息;交通地名;桥",
      "photos": [],
      "building": [],
      "typecode": "190307",
      "shopinfo": "2",
      "poiweight": [],
      "adname": "阜宁县",
      "featured_reviews_remake": [],
      "tel": [],
      "id": "B0FFFAI53Y",
      "address": "阜宁县",
      "space_num": [],
      "pname": "江苏省",
      "biz_type": [],
      "cityname": "盐城市",
      "childtype": [],
      "atag": [],
      "name": "新阜宁大桥",
      "location": "119.802427,33.773772",
      "shopid": [],
      "favorite_num": [],
      "featured_reviews": []
    },
    {
      "parent": [],
      "distance": [],
      "keytag": "快速出口",
      "importance": [],
      "biz_ext": [],
      "type": "地名地址信息;交通地名;城市快速路出口",
      "photos": [],
      "building": [],
      "typecode": "190308",
      "shopinfo": "2",
      "poiweight": [],
      "adname": "阜宁县",
      "featured_reviews_remake": [],
      "tel": [],
      "id": "BZB9QN004R",
      "address": "阜宁县",
      "space_num": [],
      "pname": "江苏省",
      "biz_type": [],
      "cityname": "盐城市",
      "childtype": [],
      "atag": [],
      "name": "阜宁出口(盐阜快速公路西北向)",
      "location": "119.859592,33.710395",
      "shopid": [],
      "favorite_num": [],
      "featured_reviews": []
    },
    {
      "parent": [],
      "distance": [],
      "keytag": "地名地址信息,地名地址信息,地名地址信息",
      "importance": [],
      "biz_ext": [],
      "type": "地名地址信息;地名地址信息;地名地址信息",
      "photos": [],
      "building": [],
      "typecode": "190000",
      "shopinfo": "2",
      "poiweight": [],
      "adname": "阜宁县",
      "featured_reviews_remake": [],
      "tel": [],
      "id": "B0FFK125ZD",
      "address": "阜宁县",
      "space_num": [],
      "pname": "江苏省",
      "biz_type": [],
      "cityname": "盐城市",
      "childtype": [],
      "atag": [],
      "name": "孔荡大爱村",
      "location": "119.620159,33.681230",
      "shopid": [],
      "favorite_num": [],
      "featured_reviews": []
    },
    {
      "parent": [],
      "distance": [],
      "keytag": "道路",
      "importance": [],
      "biz_ext": [],
      "type": "地名地址信息;交通地名;道路名",
      "photos": [],
      "building": [],
      "typecode": "190301",
      "shopinfo": "2",
      "poiweight": [],
      "adname": "阜宁县",
      "featured_reviews_remake": [],
      "tel": [],
      "id": "B0FFGJM9MI",
      "address": "阜宁县",
      "space_num": [],
      "pname": "江苏省",
      "biz_type": [],
      "cityname": "盐城市",
      "childtype": [],
      "atag": [],
      "name": "兴盛路步行街",
      "location": "119.801062,33.779546",
      "shopid": [],
      "favorite_num": [],
      "featured_reviews": []
    },
    {
      "parent": [],
      "distance": [],
      "keytag": "道路",
      "importance": [],
      "biz_ext": [],
      "type": "地名地址信息;交通地名;道路名",
      "photos": [],
      "building": [],
      "typecode": "190301",
      "shopinfo": "2",
      "poiweight": [],
      "adname": "阜宁县",
      "featured_reviews_remake": [],
      "tel": [],
      "id": "BZBAQN006E",
      "address": "阜宁县",
      "space_num": [],
      "pname": "江苏省",
      "biz_type": [],
      "cityname": "盐城市",
      "childtype": [],
      "atag": [],
      "name": "广州路",
      "location": "119.811774,33.751189",
      "shopid": [],
      "favorite_num": [],
      "featured_reviews": []
    },
    {
      "parent": [],
      "distance": [],
      "keytag": "道路",
      "importance": [],
      "biz_ext": [],
      "type": "地名地址信息;交通地名;道路名",
      "photos": [],
      "building": [],
      "typecode": "190301",
      "shopinfo": "2",
      "poiweight": [],
      "adname": "阜宁县",
      "featured_reviews_remake": [],
      "tel": [],
      "id": "B0FFH54RQ6",
      "address": "阜宁县",
      "space_num": [],
      "pname": "江苏省",
      "biz_type": [],
      "cityname": "盐城市",
      "childtype": [],
      "atag": [],
      "name": "马巷",
      "location": "119.790637,33.782281",
      "shopid": [],
      "favorite_num": [],
      "featured_reviews": []
    },
    {
      "parent": [],
      "distance": [],
      "keytag": "道路交叉口",
      "importance": [],
      "biz_ext": [],
      "type": "地名地址信息;交通地名;路口名",
      "photos": [],
      "building": [],
      "typecode": "190302",
      "shopinfo": "2",
      "poiweight": [],
      "adname": "阜宁县",
      "featured_reviews_remake": [],
      "tel": [],
      "id": "B0FFGGY34N",
      "address": "阜宁县",
      "space_num": [],
      "pname": "江苏省",
      "biz_type": [],
      "cityname": "盐城市",
      "childtype": [],
      "atag": [],
      "name": "阜城大街与阜师路交叉口",
      "location": "119.790061,33.782768",
      "shopid": [],
      "favorite_num": [],
      "featured_reviews": []
    },
    {
      "parent": [],
      "distance": [],
      "keytag": "道路",
      "importance": [],
      "biz_ext": [],
      "type": "地名地址信息;交通地名;道路名",
      "photos": [],
      "building": [],
      "typecode": "190301",
      "shopinfo": "2",
      "poiweight": [],
      "adname": "阜宁县",
      "featured_reviews_remake": [],
      "tel": [],
      "id": "B02030IJ7W",
      "address": "阜宁县",
      "space_num": [],
      "pname": "江苏省",
      "biz_type": [],
      "cityname": "盐城市",
      "childtype": [],
      "atag": [],
      "name": "阜师路",
      "location": "119.789879,33.785792",
      "shopid": [],
      "favorite_num": [],
      "featured_reviews": []
    },
    {
      "parent": [],
      "distance": [],
      "keytag": "服务区",
      "importance": [],
      "biz_ext": [],
      "type": "道路附属设施;服务区;公路驿站",
      "photos": [],
      "building": [],
      "typecode": "180303",
      "shopinfo": "2",
      "poiweight": [],
      "adname": "阜宁县",
      "featured_reviews_remake": [],
      "tel": [],
      "id": "B0L3MSJN8H",
      "address": "阜宁县",
      "space_num": [],
      "pname": "江苏省",
      "biz_type": [],
      "cityname": "盐城市",
      "childtype": [],
      "atag": [],
      "name": "马家荡服务区",
      "location": "119.627681,33.561510",
      "shopid": [],
      "favorite_num": [],
      "featured_reviews": []
    }
  ],
  "status": "1",
  "info": "OK"
}