{
  "suggestion": {
    "keywords": [],
    "cities": []
  },
  "count": "450",
  "infocode": "10000",
  "pois": [
    {
      "parent": "B0HKUHUL3B",
      "distance": [],
      "keytag": "快捷酒店",
      "importance": [],
      "biz_ext": [],
      "type": "住宿服务;宾馆酒店;宾馆酒店",
      "photos": [],
      "building": [],
      "typecode": "100100",
      "shopinfo": "1",
      "poiweight": [],
      "adname": "浦口区",
      "featured_reviews_remake": [],
      "tel": "13057602360",
      "id": "B0G0SO29HR",
      "address": "文景路99号龙湖北宸星座6栋商铺一楼106(德佑地产)",
      "space_num": [],
      "pname": "江苏省",
      "biz_type": "hotel",
      "cityname": "南京市",
      "childtype": "202",
      "atag": [],
      "name": "南京榴莲芒果公寓(星火路地铁站店)",
      "location": "118.699394,32.159320",
      "shopid": [],
      "favorite_num": [],
      "featured_reviews": []
    },
    {
      "parent": [],
      "distance": [],
      "keytag": "经济型",
      "importance": [],
      "biz_ext": [],
      "type": "住宿服务;住宿服务相关;住宿服务相关",
      "photos": [],
      "building": [],
      "typecode": "100000",
      "shopinfo": "0",
      "poiweight": [],
      "adname": "雨花台区",
      "featured_reviews_remake": [],
      "tel": "18913929027",
      "id": "B0FFL9VXOT",
      "address": "雨花西路268-1号(近安德门地铁站2号口,安德门花卉市场旁)",
      "space_num": [],
      "pname": "江苏省",
      "biz_type": "hotel",
      "cityname": "南京市",
      "childtype": [],
      "atag": [],
      "name": "菲客公寓(南京安德门地铁站店)",
      "location": "118.762224,31.994200",
      "shopid": [],
      "favorite_num": [],
      "featured_reviews": []
    },
    {
      "parent": [],
      "distance": [],
      "keytag": "经济型",
      "importance": [],
      "biz_ext": [],
      "type": "住宿服务;住宿服务相关;住宿服务相关",
      "photos": [],
      "building": [],
      "typecode": "100000",
      "shopinfo": "0",
      "poiweight": [],
      "adname": "江宁区",
      "featured_reviews_remake": [],
      "tel": "13913938552;+862126137886,70827",
      "id": "B0FFIORUC8",
      "address": "天元西路146号(天元西路地铁站3号口步行480米)",
      "space_num": [],
      "pname": "江苏省",
      "biz_type": "hotel",
      "cityname": "南京市",
      "childtype": [],
      "atag": [],
      "name": "禧樾公寓原村长公寓(天元西路分店)",
      "location": "118.804457,31.929214",
      "shopid": [],
      "favorite_num": [],
      "featured_reviews": []
    },
    {
      "parent": [],
      "distance": [],
      "keytag": "旅馆",
      "importance": [],
      "biz_ext": [],
      "type": "住宿服务;旅馆招待所;旅馆招待所",
      "photos": [],
      "building": [],
      "typecode": "100200",
      "shopinfo": "1",
      "poiweight": [],
      "adname": "秦淮区",
      "featured_reviews_remake": [],
      "tel": "15720623756",
      "id": "B0I0M747BO",
      "address": "解放路38号-11号",
      "space_num": [],
      "pname": "江苏省",
      "biz_type": "hotel",
      "cityname": "南京市",
      "childtype": [],
      "atag": [],
      "name": "迎微公寓(南京西安门地铁站东部战区总医院店)",
      "location": "118.809915,32.035550",
      "shopid": [],
      "favorite_num": [],
      "featured_reviews": []
    },
    {
      "parent": [],
      "distance": [],
      "keytag": "旅馆",
      "importance": [],
      "biz_ext": [],
      "type": "住宿服务;住宿服务相关;住宿服务相关",
      "photos": [],
      "building": [],
      "typecode": "100000",
      "shopinfo": "0",
      "poiweight": [],
      "adname": "鼓楼区",
      "featured_reviews_remake": [],
      "tel": "025-86799179",
      "id": "B0GK27J6HL",
      "address": "玉宁路16号龙湖紫都广场1栋1楼01门面",
      "space_num": [],
      "pname": "江苏省",
      "biz_type": "hotel",
      "cityname": "南京市",
      "childtype": [],
      "atag": [],
      "name": "清和影院公寓(南京火车站中央门店)",
      "location": "118.779271,32.092601",
      "shopid": [],
      "favorite_num": [],
      "featured_reviews": []
    },
    {
      "parent": [],
      "distance": [],
      "keytag": "经济型",
      "importance": [],
      "biz_ext": [],
      "type": "住宿服务;宾馆酒店;宾馆酒店",
      "photos": [],
      "building": [],
      "typecode": "100100",
      "shopinfo": "0",
      "poiweight": [],
      "adname": "玄武区",
      "featured_reviews_remake": [],
      "tel": "18012590555;18061755188",
      "id": "B0LGX58MSA",
      "address": "鹤鸣路52号(仙鹤名苑51栋77·生活广场2层)",
      "space_num": [],
      "pname": "江苏省",
      "biz_type": "hotel",
      "cityname": "南京市",
      "childtype": [],
      "atag": [],
      "name": "安柚Annyo酒店式公寓(仙林大学城仙鹤门地铁站店)",
      "location": "118.900073,32.089876",
      "shopid": [],
      "favorite_num": [],
      "featured_reviews": []
    },
    {
      "parent": [],
      "distance": [],
      "keytag": "经济型",
      "importance": [],
      "biz_ext": [],
      "type": "住宿服务;宾馆酒店;宾馆酒店",
      "photos": [],
      "building": [],
      "typecode": "100100",
      "shopinfo": "0",
      "poiweight": [],
      "adname": "鼓楼区",
      "featured_reviews_remake": [],
      "tel": "15261875618",
      "id": "B0LADZ8TS6",
      "address": "南祖师庵9号(盐仓桥地铁站3号口步行170米)",
      "space_num": [],
      "pname": "江苏省",
      "biz_type": "hotel",
      "cityname": "南京市",
      "childtype": [],
      "atag": [],
      "name": "南京享筑酒店公寓(阅江楼风景区盐仓桥地铁站店)",
      "location": "118.752690,32.084877",
      "shopid": [],
      "favorite_num": [],
      "featured_reviews": []
    },
    {
      "parent": [],
      "distance": [],
      "keytag": "经济型",
      "importance": [],
      "biz_ext": [],
      "type": "住宿服务;旅馆招待所;旅馆招待所",
      "photos": [],
      "building": [],
      "typecode": "100200",
      "shopinfo": "0",
      "poiweight": [],
      "adname": "江宁区",
      "featured_reviews_remake": [],
      "tel": "18851695631",
      "id": "B0L0R7858Q",
      "address": "竹翠路5号都荟天地B-3幢1楼120",
      "space_num": [],
      "pname": "江苏省",
      "biz_type": "hotel",
      "cityname": "南京市",
      "childtype": [],
      "atag": [],
      "name": "安荟公寓(南京南站南广场万科都荟天地城店)",
      "location": "118.796721,31.964404",
      "shopid": [],
      "favorite_num": [],
      "featured_reviews": []
    },
    {
      "parent": [],
      "distance": [],
      "keytag": "经济型",
      "importance": [],
      "biz_ext": [],
      "type": "商务住宅;商务住宅相关;商务住宅相关|住宿服务;住宿服务相关;住宿服务相关",
      "photos": [],
      "building": [],
      "typecode": "120000|100000",
      "shopinfo": "0",
      "poiweight": [],
      "adname": "雨花台区",
      "featured_reviews_remake": [],
      "tel": "18351944533;+861056320612,1011940",
      "id": "B0KRCDC2DH",
      "address": "软件大道109号雨花客厅7栋",
      "space_num": [],
      "pname": "江苏省",
      "biz_type": [],
      "cityname": "南京市",
      "childtype": [],
      "atag": [],
      "name": "雨花精品酒店式公寓(雨花客厅天隆寺地铁站店)",
      "location": "118.764910,31.980265",
      "shopid": [],
      "favorite_num": [],
      "featured_reviews": []
    },
    {
      "parent": [],
      "distance": [],
      "keytag": "经济型",
      "importance": [],
      "biz_ext": [],
      "type": "住宿服务;住宿服务相关;住宿服务相关",
      "photos": [],
      "building": [],
      "typecode": "100000",
      "shopinfo": "0",
      "poiweight": [],
      "adname": "浦口区",
      "featured_reviews_remake": [],
      "tel": "13260882287",
      "id": "B0KKDRZ7YS",
      "address": "丹桂路16号",
      "space_num": [],
      "pname": "江苏省",
      "biz_type": "hotel",
      "cityname": "南京市",
      "childtype": [],
      "atag": [],
      "name": "智枫酒店式公寓(桥林工业园店)",
      "location": "118.551110,31.953653",
      "shopid": [],
      "favorite_num": [],
      "featured_reviews": []
    },
    {
      "parent": [],
      "distance": [],
      "keytag": "经济型",
      "importance": [],
      "biz_ext": [],
      "type": "住宿服务;住宿服务相关;住宿服务相关",
      "photos": [],
      "building": [],
      "typecode": "100000",
      "shopinfo": "0",
      "poiweight": [],
      "adname": "江宁区",
      "featured_reviews_remake": [],
      "tel": "18114018280",
      "id": "B0KG1U76VK",
      "address": "东山街道竹翠路万科都荟天地B3-115室",
      "space_num": [],
      "pname": "江苏省",
      "biz_type": "hotel",
      "cityname": "南京市",
      "childtype": [],
      "atag": [],
      "name": "凯诗顿公寓(南京南站万科都荟天地店)",
      "location": "118.796977,31.964712",
      "shopid": [],
      "favorite_num": [],
      "featured_reviews": []
    },
    {
      "parent": [],
      "distance": [],
      "keytag": "经济型",
      "importance": [],
      "biz_ext": [],
      "type": "住宿服务;宾馆酒店;宾馆酒店",
      "photos": [],
      "building": [],
      "typecode": "100100",
      "shopinfo": "0",
      "poiweight": [],
      "adname": "建邺区",
      "featured_reviews_remake": [],
      "tel": "17368697968",
      "id": "B0KDXCH3WR",
      "address": "双闸街道首创天阅公馆2幢01室",
      "space_num": [],
      "pname": "江苏省",
      "biz_type": "hotel",
      "cityname": "南京市",
      "childtype": [],
      "atag": [],
      "name": "岚枫酒店公寓(河西儿童医院店)",
      "location": "118.706799,31.973647",
      "shopid": [],
      "favorite_num": [],
      "featured_reviews": []
    },
    {
      "parent": "B0GUJGPT7Y",
      "distance": [],
      "keytag": "经济型",
      "importance": [],
      "biz_ext": [],
      "type": "住宿服务;旅馆招待所;旅馆招待所",
      "photos": [],
      "building": [],
      "typecode": "100200",
      "shopinfo": "0",
      "poiweight": [],
      "adname": "江宁区",
      "featured_reviews_remake": [],
      "tel": "18512560960;+861056320612,45221680",
      "id": "B0KAB468BJ",
      "address": "鹏山路26号中粮祥云悦广场2栋",
      "space_num": [],
      "pname": "江苏省",
      "biz_type": "hotel",
      "cityname": "南京市",
      "childtype": "202",
      "atag": [],
      "name": "蓝湾假日公寓(南京江宁大学城店)",
      "location": "118.894673,31.914098",
      "shopid": [],
      "favorite_num": [],
      "featured_reviews": []
    },
    {
      "parent": "B0KGYHI24Q",
      "distance": [],
      "keytag": "经济型",
      "importance": [],
      "biz_ext": [],
      "type": "住宿服务;旅馆招待所;旅馆招待所",
      "photos": [],
      "building": [],
      "typecode": "100200",
      "shopinfo": "0",
      "poiweight": [],
      "adname": "浦口区",
      "featured_reviews_remake": [],
      "tel": "15251729689;15252498689",
      "id": "B0K6RGGAH6",
      "address": "天浦路28号江畔都会上城20栋1622室",
      "space_num": [],
      "pname": "江苏省",
      "biz_type": "hotel",
      "cityname": "南京市",
      "childtype": "202",
      "atag": [],
      "name": "蓝湾假日公寓(浦口万汇城地铁站店)",
      "location": "118.666903,32.066643",
      "shopid": [],
      "favorite_num": [],
      "featured_reviews": []
    },
    {
      "parent": "B0GUJGPT7Y",
      "distance": [],
      "keytag": "经济型",
      "importance": [],
      "biz_ext": [],
      "type": "住宿服务;旅馆招待所;旅馆招待所",
      "photos": [],
      "building": [],
      "typecode": "100200",
      "shopinfo": "0",
      "poiweight": [],
      "adname": "江宁区",
      "featured_reviews_remake": [],
      "tel": "19941513332",
      "id": "B0K6HSEKYH",
      "address": "淳化街道鹏山路26号2栋120号门面房",
      "space_num": [],
      "pname": "江苏省",
      "biz_type": "hotel",
      "cityname": "南京市",
      "childtype": "202",
      "atag": [],
      "name": "南京瑞斯特公寓(江宁大学城店)",
      "location": "118.894348,31.914265",
      "shopid": [],
      "favorite_num": [],
      "featured_reviews": []
    },
    {
      "parent": "B0FFLOAPC9",
      "distance": [],
      "keytag": "经济型",
      "importance": [],
      "biz_ext": [],
      "type": "商务住宅;商务住宅相关;商务住宅相关|住宿服务;住宿服务相关;住宿服务相关",
      "photos": [],
      "building": [],
      "typecode": "120000|100000",
      "shopinfo": "1",
      "poiweight": [],
      "adname": "雨花台区",
      "featured_reviews_remake": [],
      "tel": "17751765616",
      "id": "B0H0SZ1ZJD",
      "address": "石华街5号103室",
      "space_num": [],
      "pname": "江苏省",
      "biz_type": [],
      "cityname": "南京市",
      "childtype": "202",
      "atag": [],
      "name": "众尚易居运动主题影院公寓(南京南站北广场店)",
      "location": "118.792333,31.971094",
      "shopid": [],
      "favorite_num": [],
      "featured_reviews": []
    },
    {
      "parent": [],
      "distance": [],
      "keytag": "经济型",
      "importance": [],
      "biz_ext": [],
      "type": "住宿服务;住宿服务相关;住宿服务相关",
      "photos": [],
      "building": [],
      "typecode": "100000",
      "shopinfo": "0",
      "poiweight": [],
      "adname": "雨花台区",
      "featured_reviews_remake": [],
      "tel": "13921418838",
      "id": "B0G0TKD4BT",
      "address": "软件大道38号绿地云尚公馆A2幢3号门3楼332室",
      "space_num": [],
      "pname": "江苏省",
      "biz_type": "hotel",
      "cityname": "南京市",
      "childtype": [],
      "atag": [],
      "name": "尚好酒店公寓(南京南站花神庙地铁站店)",
      "location": "118.789908,31.978046",
      "shopid": [],
      "favorite_num": [],
      "featured_reviews": []
    },
    {
      "parent": "B0FFG271BL",
      "distance": [],
      "keytag": "经济型",
      "importance": [],
      "biz_ext": [],
      "type": "住宿服务;住宿服务相关;住宿服务相关",
      "photos": [],
      "building": [],
      "typecode": "100000",
      "shopinfo": "0",
      "poiweight": [],
      "adname": "秦淮区",
      "featured_reviews_remake": [],
      "tel": "025-85875018;+862126137886,6263664",
      "id": "B0FFINOOGV",
      "address": "中华路1号观城国际北楼6层601",
      "space_num": [],
      "pname": "江苏省",
      "biz_type": "hotel",
      "cityname": "南京市",
      "childtype": "202",
      "atag": [],
      "name": "摩兜公寓(南京夫子庙店)",
      "location": "118.786544,32.028123",
      "shopid": [],
      "favorite_num": [],
      "featured_reviews": []
    },
    {
      "parent": [],
      "distance": [],
      "keytag": "经济型",
      "importance": [],
      "biz_ext": [],
      "type": "住宿服务;宾馆酒店;宾馆酒店",
      "photos": [],
      "building": [],
      "typecode": "100100",
      "shopinfo": "0",
      "poiweight": [],
      "adname": "雨花台区",
      "featured_reviews_remake": [],
      "tel": "13390777129",
      "id": "B0FFFQZU2R",
      "address": "雨花西路35号(中华门地铁站3号口步行100米)",
      "space_num": [],
      "pname": "江苏省",
      "biz_type": "hotel",
      "cityname": "南京市",
      "childtype": [],
      "atag": [],
      "name": "苏博公寓(中华门地铁站店)",
      "location": "118.774303,32.005327",
      "shopid": [],
      "favorite_num": [],
      "featured_reviews": []
    },
    {
      "parent": [],
      "distance": [],
      "keytag": "经济型",
      "importance": [],
      "biz_ext": [],
      "type": "住宿服务;宾馆酒店;宾馆酒店",
      "photos": [],
      "building": [],
      "typecode": "100100",
      "shopinfo": "0",
      "poiweight": [],
      "adname": "栖霞区",
      "featured_reviews_remake": [],
      "tel": "13815401277",
      "id": "B0LBC5AJC1",
      "address": "翠林南路与金尧路交叉口东南100米",
      "space_num": [],
      "pname": "江苏省",
      "biz_type": "hotel",
      "cityname": "南京市",
      "childtype": [],
      "atag": [],
      "name": "艾米家酒店公寓(尧化门店)",
      "location": "118.887879,32.125910",
      "shopid": [],
      "favorite_num": [],
      "featured_reviews": []
    }
  ],
  "status": "1",
  "info": "OK"
}