{
  "suggestion": {
    "keywords": [],
    "cities": []
  },
  "count": "100",
  "infocode": "10000",
  "pois": [
    {
      "parent": [],
      "distance": [],
      "keytag": "工业园区",
      "importance": [],
      "biz_ext": [],
      "type": "商务住宅;产业园区;产业园区",
      "photos": [],
      "building": [],
      "typecode": "120100",
      "shopinfo": "0",
      "poiweight": [],
      "adname": "太仓市",
      "featured_reviews_remake": [],
      "tel": [],
      "id": "B0LG41FFW7",
      "address": "沙溪镇沙鹿路288号",
      "space_num": [],
      "pname": "江苏省",
      "biz_type": [],
      "cityname": "苏州市",
      "childtype": [],
      "atag": [],
      "name": "太仓市工业园区",
      "location": "121.087925,31.589275",
      "shopid": [],
      "favorite_num": [],
      "featured_reviews": []
    },
    {
      "parent": [],
      "distance": [],
      "keytag": "工业园区",
      "importance": [],
      "biz_ext": [],
      "type": "商务住宅;产业园区;产业园区",
      "photos": [],
      "building": [],
      "typecode": "120100",
      "shopinfo": "0",
      "poiweight": [],
      "adname": "吴中区",
      "featured_reviews_remake": [],
      "tel": "0512-62886666",
      "id": "B0LA49BEPP",
      "address": "夷陵山街与阳澄湖大道交叉口东南80米",
      "space_num": [],
      "pname": "江苏省",
      "biz_type": [],
      "cityname": "苏州市",
      "childtype": [],
      "atag": [],
      "name": "吴中区工业园区",
      "location": "120.804225,31.373325",
      "shopid": [],
      "favorite_num": [],
      "featured_reviews": []
    },
    {
      "parent": [],
      "distance": [],
      "keytag": "工业园区",
      "importance": [],
      "biz_ext": [],
      "type": "商务住宅;产业园区;产业园区",
      "photos": [],
      "building": [],
      "typecode": "120100",
      "shopinfo": "0",
      "poiweight": [],
      "adname": "吴中区",
      "featured_reviews_remake": [],
      "tel": [],
      "id": "B0L0Z7FE26",
      "address": "金鸡湖大道与淞江路交叉口西北280米",
      "space_num": [],
      "pname": "江苏省",
      "biz_type": [],
      "cityname": "苏州市",
      "childtype": [],
      "atag": [],
      "name": "斜塘镇工业园区",
      "location": "120.721325,31.301175",
      "shopid": [],
      "favorite_num": [],
      "featured_reviews": []
    },
    {
      "parent": [],
      "distance": [],
      "keytag": "工业园区",
      "importance": [],
      "biz_ext": [],
      "type": "商务住宅;产业园区;产业园区",
      "photos": [],
      "building": [],
      "typecode": "120100",
      "shopinfo": "0",
      "poiweight": [],
      "adname": "常熟市",
      "featured_reviews_remake": [],
      "tel": [],
      "id": "B0FFFSDKXR",
      "address": "和莫路与元和路辅路交叉口南320米",
      "space_num": [],
      "pname": "江苏省",
      "biz_type": [],
      "cityname": "苏州市",
      "childtype": [],
      "atag": [],
      "name": "元和园工业园区",
      "location": "120.714129,31.619589",
      "shopid": [],
      "favorite_num": [],
      "featured_reviews": []
    },
    {
      "parent": [],
      "distance": [],
      "keytag": "图书馆",
      "importance": [],
      "biz_ext": [],
      "type": "科教文化服务;图书馆;图书馆",
      "photos": [],
      "building": [],
      "typecode": "140500",
      "shopinfo": "0",
      "poiweight": [],
      "adname": "虎丘区",
      "featured_reviews_remake": [],
      "tel": "0512-65934206;0512-65936697;4008856697",
      "id": "B0FFK4LF18",
      "address": "苏州工业园区仁爱路258号",
      "space_num": [],
      "pname": "江苏省",
      "biz_type": [],
      "cityname": "苏州市",
      "childtype": [],
      "atag": [],
      "name": "工业园区图书馆(总馆)",
      "location": "120.722260,31.276318",
      "shopid": [],
      "favorite_num": [],
      "featured_reviews": []
    },
    {
      "parent": [],
      "distance": [],
      "keytag": "工业园区",
      "importance": [],
      "biz_ext": [],
      "type": "商务住宅;产业园区;产业园区",
      "photos": [],
      "building": [],
      "typecode": "120100",
      "shopinfo": "0",
      "poiweight": [],
      "adname": "昆山市",
      "featured_reviews_remake": [],
      "tel": [],
      "id": "B0FFFRYPL4",
      "address": "青阳北路319号",
      "space_num": [],
      "pname": "江苏省",
      "biz_type": [],
      "cityname": "苏州市",
      "childtype": [],
      "atag": [],
      "name": "松港工业园昆山园区",
      "location": "120.993686,31.429519",
      "shopid": [],
      "favorite_num": [],
      "featured_reviews": []
    },
    {
      "parent": [],
      "distance": [],
      "keytag": "工业园区",
      "importance": [],
      "biz_ext": [],
      "type": "商务住宅;产业园区;产业园区",
      "photos": [],
      "building": [],
      "typecode": "120100",
      "shopinfo": "0",
      "poiweight": [],
      "adname": "昆山市",
      "featured_reviews_remake": [],
      "tel": [],
      "id": "B02001744V",
      "address": "花桥经济开发区鸡鸣塘南路936号",
      "space_num": [],
      "pname": "江苏省",
      "biz_type": [],
      "cityname": "苏州市",
      "childtype": [],
      "atag": [],
      "name": "和椿工业园区",
      "location": "121.125535,31.311942",
      "shopid": [],
      "favorite_num": [],
      "featured_reviews": []
    },
    {
      "parent": [],
      "distance": [],
      "keytag": "工业园区",
      "importance": [],
      "biz_ext": [],
      "type": "商务住宅;产业园区;产业园区",
      "photos": [],
      "building": [],
      "typecode": "120100",
      "shopinfo": "0",
      "poiweight": [],
      "adname": "吴中区",
      "featured_reviews_remake": [],
      "tel": [],
      "id": "B0HDLMVDOH",
      "address": "现代大道与后戴街交叉口东北40米",
      "space_num": [],
      "pname": "江苏省",
      "biz_type": [],
      "cityname": "苏州市",
      "childtype": [],
      "atag": [],
      "name": "苏州工业园区高端制造与国际贸易区",
      "location": "120.824009,31.339436",
      "shopid": [],
      "favorite_num": [],
      "featured_reviews": []
    },
    {
      "parent": [],
      "distance": [],
      "keytag": "寺庙",
      "importance": [],
      "biz_ext": [],
      "type": "风景名胜;风景名胜;寺庙道观",
      "photos": [],
      "building": [],
      "typecode": "110205",
      "shopinfo": "2",
      "poiweight": [],
      "adname": "虎丘区",
      "featured_reviews_remake": [],
      "tel": [],
      "id": "B0FFI2ULON",
      "address": "苏州工业园区群星二路",
      "space_num": [],
      "pname": "江苏省",
      "biz_type": "tour",
      "cityname": "苏州市",
      "childtype": [],
      "atag": [],
      "name": "苏州工业园区积善寺",
      "location": "120.672052,31.269929",
      "shopid": [],
      "favorite_num": [],
      "featured_reviews": []
    },
    {
      "parent": [],
      "distance": [],
      "keytag": "工业园区",
      "importance": [],
      "biz_ext": [],
      "type": "商务住宅;产业园区;产业园区",
      "photos": [],
      "building": [],
      "typecode": "120100",
      "shopinfo": "0",
      "poiweight": [],
      "adname": "常熟市",
      "featured_reviews_remake": [],
      "tel": [],
      "id": "B0L067NIR4",
      "address": "莫城大道528号",
      "space_num": [],
      "pname": "江苏省",
      "biz_type": [],
      "cityname": "苏州市",
      "childtype": [],
      "atag": [],
      "name": "528云锦城产业园",
      "location": "120.728904,31.604722",
      "shopid": [],
      "favorite_num": [],
      "featured_reviews": []
    },
    {
      "parent": "B0FFF4N45K",
      "distance": [],
      "keytag": "写字楼",
      "importance": [],
      "biz_ext": [],
      "type": "商务住宅;楼宇;商务写字楼",
      "photos": [],
      "building": [],
      "typecode": "120201",
      "shopinfo": "0",
      "poiweight": [],
      "adname": "吴中区",
      "featured_reviews_remake": [],
      "tel": [],
      "id": "B0FFL2UCKE",
      "address": "苏州工业园区思安街",
      "space_num": [],
      "pname": "江苏省",
      "biz_type": [],
      "cityname": "苏州市",
      "childtype": "308",
      "atag": [],
      "name": "苏州市苏州工业园区吴中区丰隆城市中心T3座",
      "location": "120.717719,31.317720",
      "shopid": [],
      "favorite_num": [],
      "featured_reviews": []
    },
    {
      "parent": "B02000IVHV",
      "distance": [],
      "keytag": "人才服务",
      "importance": [],
      "biz_ext": [],
      "type": "生活服务;人才市场;人才市场",
      "photos": [],
      "building": [],
      "typecode": "070800",
      "shopinfo": "0",
      "poiweight": [],
      "adname": "吴中区",
      "featured_reviews_remake": [],
      "tel": "4006000600",
      "id": "B0200079W8",
      "address": "苏州工业园区旺墩路168号市场大厦",
      "space_num": [],
      "pname": "江苏省",
      "biz_type": [],
      "cityname": "苏州市",
      "childtype": "202",
      "atag": [],
      "name": "苏州市工业园区人力资源市场",
      "location": "120.724120,31.320394",
      "shopid": [],
      "favorite_num": [],
      "featured_reviews": []
    },
    {
      "parent": [],
      "distance": [],
      "keytag": "工业园区",
      "importance": [],
      "biz_ext": [],
      "type": "商务住宅;产业园区;产业园区",
      "photos": [],
      "building": [],
      "typecode": "120100",
      "shopinfo": "0",
      "poiweight": [],
      "adname": "虎丘区",
      "featured_reviews_remake": [],
      "tel": [],
      "id": "B0FFF2R9VS",
      "address": "苏州工业园区松涛街208号苏州工业园区工业技术学校",
      "space_num": [],
      "pname": "江苏省",
      "biz_type": [],
      "cityname": "苏州市",
      "childtype": [],
      "atag": [],
      "name": "苏州工业园区工业技术学校创业园",
      "location": "120.745304,31.260055",
      "shopid": [],
      "favorite_num": [],
      "featured_reviews": []
    },
    {
      "parent": [],
      "distance": [],
      "keytag": "工业园区",
      "importance": [],
      "biz_ext": [],
      "type": "商务住宅;产业园区;产业园区",
      "photos": [],
      "building": [],
      "typecode": "120100",
      "shopinfo": "0",
      "poiweight": [],
      "adname": "太仓市",
      "featured_reviews_remake": [],
      "tel": [],
      "id": "B020015V4L",
      "address": "太仓市开发区人民北路166号",
      "space_num": [],
      "pname": "江苏省",
      "biz_type": [],
      "cityname": "苏州市",
      "childtype": [],
      "atag": [],
      "name": "北郊工业园",
      "location": "121.086915,31.476781",
      "shopid": [],
      "favorite_num": [],
      "featured_reviews": []
    },
    {
      "parent": [],
      "distance": [],
      "keytag": "工业园区",
      "importance": [],
      "biz_ext": [],
      "type": "商务住宅;产业园区;产业园区",
      "photos": [],
      "building": [],
      "typecode": "120100",
      "shopinfo": "0",
      "poiweight": [],
      "adname": "昆山市",
      "featured_reviews_remake": [],
      "tel": [],
      "id": "B0FFG7CH7S",
      "address": "周市镇明达路100号2号厂房",
      "space_num": [],
      "pname": "江苏省",
      "biz_type": [],
      "cityname": "苏州市",
      "childtype": [],
      "atag": [],
      "name": "欣臻沁工业园区",
      "location": "121.022412,31.415272",
      "shopid": [],
      "favorite_num": [],
      "featured_reviews": []
    },
    {
      "parent": [],
      "distance": [],
      "keytag": "工业园区",
      "importance": [],
      "biz_ext": [],
      "type": "商务住宅;产业园区;产业园区",
      "photos": [],
      "building": [],
      "typecode": "120100",
      "shopinfo": "1",
      "poiweight": [],
      "adname": "吴中区",
      "featured_reviews_remake": [],
      "tel": "0512-69997888",
      "id": "B0FFFSD9RX",
      "address": "苏州工业园区唯新路60号",
      "space_num": [],
      "pname": "江苏省",
      "biz_type": [],
      "cityname": "苏州市",
      "childtype": [],
      "atag": [],
      "name": "启迪时尚科技城",
      "location": "120.728192,31.360702",
      "shopid": [],
      "favorite_num": [],
      "featured_reviews": []
    },
    {
      "parent": [],
      "distance": [],
      "keytag": "工业园区",
      "importance": [],
      "biz_ext": [],
      "type": "商务住宅;产业园区;产业园区",
      "photos": [],
      "building": [],
      "typecode": "120100",
      "shopinfo": "0",
      "poiweight": [],
      "adname": "常熟市",
      "featured_reviews_remake": [],
      "tel": [],
      "id": "B0JB31E4SV",
      "address": "永嘉路与金茂路交叉口东80米",
      "space_num": [],
      "pname": "江苏省",
      "biz_type": [],
      "cityname": "苏州市",
      "childtype": [],
      "atag": [],
      "name": "新龙腾工业园区",
      "location": "120.942539,31.746896",
      "shopid": [],
      "favorite_num": [],
      "featured_reviews": []
    },
    {
      "parent": [],
      "distance": [],
      "keytag": "工业园区",
      "importance": [],
      "biz_ext": [],
      "type": "商务住宅;产业园区;产业园区",
      "photos": [],
      "building": [],
      "typecode": "120100",
      "shopinfo": "0",
      "poiweight": [],
      "adname": "太仓市",
      "featured_reviews_remake": [],
      "tel": [],
      "id": "B02001D4BM",
      "address": "南京东路3号",
      "space_num": [],
      "pname": "江苏省",
      "biz_type": [],
      "cityname": "苏州市",
      "childtype": [],
      "atag": [],
      "name": "大成工业园(南京东路)",
      "location": "121.103758,31.473120",
      "shopid": [],
      "favorite_num": [],
      "featured_reviews": []
    },
    {
      "parent": [],
      "distance": [],
      "keytag": "工业园区",
      "importance": [],
      "biz_ext": [],
      "type": "商务住宅;产业园区;产业园区",
      "photos": [],
      "building": [],
      "typecode": "120100",
      "shopinfo": "0",
      "poiweight": [],
      "adname": "昆山市",
      "featured_reviews_remake": [],
      "tel": "0512-82622200",
      "id": "B0FFGBEVXY",
      "address": "锦溪镇锦东路288号",
      "space_num": [],
      "pname": "江苏省",
      "biz_type": [],
      "cityname": "苏州市",
      "childtype": [],
      "atag": [],
      "name": "立讯精密(昆山)有限公司工业园区",
      "location": "120.954455,31.183408",
      "shopid": [],
      "favorite_num": [],
      "featured_reviews": []
    },
    {
      "parent": "B0FFG6QP8M",
      "distance": [],
      "keytag": "工业园区",
      "importance": [],
      "biz_ext": [],
      "type": "商务住宅;产业园区;产业园区",
      "photos": [],
      "building": [],
      "typecode": "120100",
      "shopinfo": "0",
      "poiweight": [],
      "adname": "虎丘区",
      "featured_reviews_remake": [],
      "tel": [],
      "id": "B0J1JUWG9B",
      "address": "苏州工业园区金鸡湖大道99号纳米科技城西北区20幢108",
      "space_num": [],
      "pname": "江苏省",
      "biz_type": [],
      "cityname": "苏州市",
      "childtype": "602",
      "atag": [],
      "name": "苏州纳米城西北区",
      "location": "120.772721,31.288991",
      "shopid": [],
      "favorite_num": [],
      "featured_reviews": []
    }
  ],
  "status": "1",
  "info": "OK"
}